<annotation>
	<folder>top건더기국류뚝배기q4</folder>
	<filename>top_건더기국류_뚝배기_삼계탕_Q4_00017.JPG</filename>
	<path>/top건더기국류뚝배기삼계탕q4/top_건더기국류_뚝배기_삼계탕_Q4_00017.JPG</path>
	<source>
		<database>fooddata</database>
	</source>
	<size>
		<width>5472</width>
		<height>3648</height>
		<depth>3</depth>
	</size>
	<object>
		<name>ref_spoon</name>
		<bndbox>
			<xmin>3755</xmin>
			<ymin>362</ymin>
			<xmax>4236</xmax>
			<ymax>1143</ymax>
		</bndbox>
	</object>
	<object>
		<name>ref_fork</name>
		<bndbox>
			<xmin>4479</xmin>
			<ymin>438</ymin>
			<xmax>4812</xmax>
			<ymax>1305</ymax>
		</bndbox>
	</object>
	<object>
		<name>ref_coin</name>
		<bndbox>
			<xmin>2717</xmin>
			<ymin>2943</ymin>
			<xmax>3098</xmax>
			<ymax>3329</ymax>
		</bndbox>
	</object>
	<object>
		<name>dish</name>
		<bndbox>
			<xmin>531</xmin>
			<ymin>248</ymin>
			<xmax>3374</xmax>
			<ymax>3024</ymax>
		</bndbox>
	</object>
	<object>
		<name>삼계탕</name>
		<bndbox>
			<xmin>826</xmin>
			<ymin>552</ymin>
			<xmax>3069</xmax>
			<ymax>2753</ymax>
		</bndbox>
	</object>
</annotation>