<annotation>
	<folder>top육류부피배달종이박스치킨윙q3</folder>
	<filename>top_육류부피_배달종이박스_치킨윙_Q3_00006.JPG</filename>
	<path>/top육류부피배달종이박스치킨윙q3/top_육류부피_배달종이박스_치킨윙_Q3_00006.JPG</path>
	<source>
		<database>fooddata</database>
	</source>
	<size>
		<width>3008</width>
		<height>2000</height>
		<depth>3</depth>
	</size>
	<object>
		<name>ref_spoon</name>
		<bndbox>
			<xmin>2052</xmin>
			<ymin>111</ymin>
			<xmax>2305</xmax>
			<ymax>496</ymax>
		</bndbox>
	</object>
	<object>
		<name>ref_fork</name>
		<bndbox>
			<xmin>2371</xmin>
			<ymin>292</ymin>
			<xmax>2553</xmax>
			<ymax>713</ymax>
		</bndbox>
	</object>
	<object>
		<name>ref_coin</name>
		<bndbox>
			<xmin>1108</xmin>
			<ymin>1671</ymin>
			<xmax>1307</xmax>
			<ymax>1867</ymax>
		</bndbox>
	</object>
	<object>
		<name>dish</name>
		<bndbox>
			<xmin>730</xmin>
			<ymin>238</ymin>
			<xmax>2027</xmax>
			<ymax>1575</ymax>
		</bndbox>
	</object>
	<object>
		<name>치킨윙</name>
		<bndbox>
			<xmin>907</xmin>
			<ymin>445</ymin>
			<xmax>1809</xmax>
			<ymax>1447</ymax>
		</bndbox>
	</object>
</annotation>