<annotation>
	<folder>top비빔밥덮밥류접시류산슬덮밥q2</folder>
	<filename>top_비빔밥덮밥류_접시_류산슬덮밥_Q2_00040.JPG</filename>
	<path>/top비빔밥덮밥류접시류산슬덮밥q2/top_비빔밥덮밥류_접시_류산슬덮밥_Q2_00040.JPG</path>
	<source>
		<database>fooddata</database>
	</source>
	<size>
		<width>3008</width>
		<height>2000</height>
		<depth>3</depth>
	</size>
	<object>
		<name>ref_spoon</name>
		<bndbox>
			<xmin>413</xmin>
			<ymin>197</ymin>
			<xmax>688</xmax>
			<ymax>678</ymax>
		</bndbox>
	</object>
	<object>
		<name>ref_fork</name>
		<bndbox>
			<xmin>755</xmin>
			<ymin>242</ymin>
			<xmax>938</xmax>
			<ymax>765</ymax>
		</bndbox>
	</object>
	<object>
		<name>ref_coin</name>
		<bndbox>
			<xmin>2466</xmin>
			<ymin>912</ymin>
			<xmax>2674</xmax>
			<ymax>1113</ymax>
		</bndbox>
	</object>
	<object>
		<name>dish</name>
		<bndbox>
			<xmin>869</xmin>
			<ymin>320</ymin>
			<xmax>2210</xmax>
			<ymax>1611</ymax>
		</bndbox>
	</object>
	<object>
		<name>류산슬덮밥</name>
		<bndbox>
			<xmin>1022</xmin>
			<ymin>462</ymin>
			<xmax>1967</xmax>
			<ymax>1489</ymax>
		</bndbox>
	</object>
</annotation>