<annotation>
	<folder>top어육류면적철판닭갈비q1</folder>
	<filename>top_어육류면적_철판_닭갈비_Q1_00004.JPG</filename>
	<path>/top어육류면적철판닭갈비q1/top_어육류면적_철판_닭갈비_Q1_00004.JPG</path>
	<source>
		<database>fooddata</database>
	</source>
	<size>
		<width>3008</width>
		<height>2000</height>
		<depth>3</depth>
	</size>
	<object>
		<name>ref_spoon</name>
		<bndbox>
			<xmin>2050</xmin>
			<ymin>215</ymin>
			<xmax>2276</xmax>
			<ymax>632</ymax>
		</bndbox>
	</object>
	<object>
		<name>ref_fork</name>
		<bndbox>
			<xmin>2334</xmin>
			<ymin>210</ymin>
			<xmax>2493</xmax>
			<ymax>663</ymax>
		</bndbox>
	</object>
	<object>
		<name>ref_coin</name>
		<bndbox>
			<xmin>830</xmin>
			<ymin>1524</ymin>
			<xmax>1016</xmax>
			<ymax>1705</ymax>
		</bndbox>
	</object>
	<object>
		<name>dish</name>
		<bndbox>
			<xmin>710</xmin>
			<ymin>82</ymin>
			<xmax>1961</xmax>
			<ymax>1444</ymax>
		</bndbox>
	</object>
	<object>
		<name>닭갈비</name>
		<bndbox>
			<xmin>870</xmin>
			<ymin>463</ymin>
			<xmax>1575</xmax>
			<ymax>1146</ymax>
		</bndbox>
	</object>
</annotation>