<annotation>
	<folder>side기타튀김접시새우튀김q4</folder>
	<filename>side_기타튀김_접시_새우튀김_Q4_00033.JPG</filename>
	<path>/side기타튀김접시새우튀김q4/side_기타튀김_접시_새우튀김_Q4_00033.JPG</path>
	<source>
		<database>fooddata</database>
	</source>
	<size>
		<width>3008</width>
		<height>2000</height>
		<depth>3</depth>
	</size>
	<object>
		<name>ref_spoon</name>
		<bndbox>
			<xmin>909</xmin>
			<ymin>1601</ymin>
			<xmax>1399</xmax>
			<ymax>1877</ymax>
		</bndbox>
	</object>
	<object>
		<name>ref_fork</name>
		<bndbox>
			<xmin>930</xmin>
			<ymin>1376</ymin>
			<xmax>1446</xmax>
			<ymax>1619</ymax>
		</bndbox>
	</object>
	<object>
		<name>ref_coin</name>
		<bndbox>
			<xmin>1860</xmin>
			<ymin>163</ymin>
			<xmax>2067</xmax>
			<ymax>301</ymax>
		</bndbox>
	</object>
	<object>
		<name>dish</name>
		<bndbox>
			<xmin>952</xmin>
			<ymin>287</ymin>
			<xmax>2459</xmax>
			<ymax>1230</ymax>
		</bndbox>
	</object>
	<object>
		<name>새우튀김</name>
		<bndbox>
			<xmin>1254</xmin>
			<ymin>370</ymin>
			<xmax>2205</xmax>
			<ymax>1118</ymax>
		</bndbox>
	</object>
</annotation>