<annotation>
	<folder>top밥류밥그릇오곡밥q5</folder>
	<filename>top_밥류_밥그릇_오곡밥_Q5_00026.JPG</filename>
	<path>/top밥류밥그릇오곡밥q5/top_밥류_밥그릇_오곡밥_Q5_00026.JPG</path>
	<source>
		<database>fooddata</database>
	</source>
	<size>
		<width>5472</width>
		<height>3648</height>
		<depth>3</depth>
	</size>
	<object>
		<name>ref_spoon</name>
		<bndbox>
			<xmin>1540</xmin>
			<ymin>2647</ymin>
			<xmax>2569</xmax>
			<ymax>3219</ymax>
		</bndbox>
	</object>
	<object>
		<name>ref_fork</name>
		<bndbox>
			<xmin>1528</xmin>
			<ymin>2046</ymin>
			<xmax>2647</xmax>
			<ymax>2409</ymax>
		</bndbox>
	</object>
	<object>
		<name>ref_coin</name>
		<bndbox>
			<xmin>4248</xmin>
			<ymin>844</ymin>
			<xmax>4587</xmax>
			<ymax>1201</ymax>
		</bndbox>
	</object>
	<object>
		<name>dish</name>
		<bndbox>
			<xmin>2159</xmin>
			<ymin>160</ymin>
			<xmax>3920</xmax>
			<ymax>1898</ymax>
		</bndbox>
	</object>
	<object>
		<name>오곡밥</name>
		<bndbox>
			<xmin>2254</xmin>
			<ymin>261</ymin>
			<xmax>3837</xmax>
			<ymax>1820</ymax>
		</bndbox>
	</object>
</annotation>