<annotation>
	<folder>top육류부피배달종이박스닭튀김q3</folder>
	<filename>top_육류부피_배달종이박스_닭튀김_Q3_00029.JPG</filename>
	<path>/top육류부피배달종이박스닭튀김q3/top_육류부피_배달종이박스_닭튀김_Q3_00029.JPG</path>
	<source>
		<database>fooddata</database>
	</source>
	<size>
		<width>3008</width>
		<height>2000</height>
		<depth>3</depth>
	</size>
	<object>
		<name>ref_spoon</name>
		<bndbox>
			<xmin>859</xmin>
			<ymin>1526</ymin>
			<xmax>1280</xmax>
			<ymax>1813</ymax>
		</bndbox>
	</object>
	<object>
		<name>ref_fork</name>
		<bndbox>
			<xmin>930</xmin>
			<ymin>1292</ymin>
			<xmax>1372</xmax>
			<ymax>1496</ymax>
		</bndbox>
	</object>
	<object>
		<name>ref_coin</name>
		<bndbox>
			<xmin>940</xmin>
			<ymin>765</ymin>
			<xmax>1124</xmax>
			<ymax>942</ymax>
		</bndbox>
	</object>
	<object>
		<name>dish</name>
		<bndbox>
			<xmin>1213</xmin>
			<ymin>131</ymin>
			<xmax>2153</xmax>
			<ymax>1363</ymax>
		</bndbox>
	</object>
	<object>
		<name>닭튀김</name>
		<bndbox>
			<xmin>1352</xmin>
			<ymin>357</ymin>
			<xmax>1961</xmax>
			<ymax>1272</ymax>
		</bndbox>
	</object>
</annotation>