<annotation>
	<folder>top어육류정형철판햄버거스테이크q5</folder>
	<filename>top_어육류정형_철판_햄버거스테이크_Q5_00042.JPG</filename>
	<path>/top어육류정형철판햄버거스테이크q5/top_어육류정형_철판_햄버거스테이크_Q5_00042.JPG</path>
	<source>
		<database>fooddata</database>
	</source>
	<size>
		<width>3008</width>
		<height>2000</height>
		<depth>3</depth>
	</size>
	<object>
		<name>ref_spoon</name>
		<bndbox>
			<xmin>209</xmin>
			<ymin>238</ymin>
			<xmax>473</xmax>
			<ymax>651</ymax>
		</bndbox>
	</object>
	<object>
		<name>ref_fork</name>
		<bndbox>
			<xmin>573</xmin>
			<ymin>273</ymin>
			<xmax>747</xmax>
			<ymax>731</ymax>
		</bndbox>
	</object>
	<object>
		<name>ref_coin</name>
		<bndbox>
			<xmin>847</xmin>
			<ymin>1712</ymin>
			<xmax>1036</xmax>
			<ymax>1901</ymax>
		</bndbox>
	</object>
	<object>
		<name>dish</name>
		<bndbox>
			<xmin>931</xmin>
			<ymin>338</ymin>
			<xmax>2112</xmax>
			<ymax>1508</ymax>
		</bndbox>
	</object>
	<object>
		<name>햄버거스테이크</name>
		<bndbox>
			<xmin>1046</xmin>
			<ymin>512</ymin>
			<xmax>1972</xmax>
			<ymax>1378</ymax>
		</bndbox>
	</object>
</annotation>