<annotation>
	<folder>top국류대접시래기된장국q4</folder>
	<filename>top_국류_대접_시래기된장국_Q4_00019.JPG</filename>
	<path>/top국류대접시래기된장국q4/top_국류_대접_시래기된장국_Q4_00019.JPG</path>
	<source>
		<database>fooddata</database>
	</source>
	<size>
		<width>5472</width>
		<height>3648</height>
		<depth>3</depth>
	</size>
	<object>
		<name>ref_spoon</name>
		<bndbox>
			<xmin>1771</xmin>
			<ymin>3079</ymin>
			<xmax>2492</xmax>
			<ymax>3567</ymax>
		</bndbox>
	</object>
	<object>
		<name>ref_fork</name>
		<bndbox>
			<xmin>1847</xmin>
			<ymin>2617</ymin>
			<xmax>2619</xmax>
			<ymax>2937</ymax>
		</bndbox>
	</object>
	<object>
		<name>ref_coin</name>
		<bndbox>
			<xmin>4347</xmin>
			<ymin>1123</ymin>
			<xmax>4662</xmax>
			<ymax>1438</ymax>
		</bndbox>
	</object>
	<object>
		<name>dish</name>
		<bndbox>
			<xmin>2182</xmin>
			<ymin>188</ymin>
			<xmax>4235</xmax>
			<ymax>2195</ymax>
		</bndbox>
	</object>
	<object>
		<name>시래기된장국</name>
		<bndbox>
			<xmin>2324</xmin>
			<ymin>371</ymin>
			<xmax>4037</xmax>
			<ymax>2098</ymax>
		</bndbox>
	</object>
</annotation>