<annotation>
	<folder>side부침개류사각배달달걀말이q4</folder>
	<filename>side_부침개류_사각배달_달걀말이_Q4_00035.JPG</filename>
	<path>/side부침개류사각배달달걀말이q4/side_부침개류_사각배달_달걀말이_Q4_00035.JPG</path>
	<source>
		<database>fooddata</database>
	</source>
	<size>
		<width>3008</width>
		<height>2000</height>
		<depth>3</depth>
	</size>
	<object>
		<name>ref_spoon</name>
		<bndbox>
			<xmin>346</xmin>
			<ymin>510</ymin>
			<xmax>617</xmax>
			<ymax>834</ymax>
		</bndbox>
	</object>
	<object>
		<name>ref_fork</name>
		<bndbox>
			<xmin>650</xmin>
			<ymin>522</ymin>
			<xmax>836</xmax>
			<ymax>903</ymax>
		</bndbox>
	</object>
	<object>
		<name>ref_coin</name>
		<bndbox>
			<xmin>1638</xmin>
			<ymin>1607</ymin>
			<xmax>1868</xmax>
			<ymax>1773</ymax>
		</bndbox>
	</object>
	<object>
		<name>dish</name>
		<bndbox>
			<xmin>876</xmin>
			<ymin>421</ymin>
			<xmax>2508</xmax>
			<ymax>1417</ymax>
		</bndbox>
	</object>
	<object>
		<name>달걀말이</name>
		<bndbox>
			<xmin>1164</xmin>
			<ymin>761</ymin>
			<xmax>2075</xmax>
			<ymax>1287</ymax>
		</bndbox>
	</object>
</annotation>