<annotation>
	<folder>top어육류면적사각배달훈제연어q2</folder>
	<filename>top_어육류면적_사각배달_훈제연어_Q2_00030.JPG</filename>
	<path>/top어육류면적사각배달훈제연어q2/top_어육류면적_사각배달_훈제연어_Q2_00030.JPG</path>
	<source>
		<database>fooddata</database>
	</source>
	<size>
		<width>3008</width>
		<height>2000</height>
		<depth>3</depth>
	</size>
	<object>
		<name>ref_spoon</name>
		<bndbox>
			<xmin>688</xmin>
			<ymin>1501</ymin>
			<xmax>1083</xmax>
			<ymax>1785</ymax>
		</bndbox>
	</object>
	<object>
		<name>ref_fork</name>
		<bndbox>
			<xmin>794</xmin>
			<ymin>1275</ymin>
			<xmax>1233</xmax>
			<ymax>1461</ymax>
		</bndbox>
	</object>
	<object>
		<name>ref_coin</name>
		<bndbox>
			<xmin>470</xmin>
			<ymin>441</ymin>
			<xmax>665</xmax>
			<ymax>632</ymax>
		</bndbox>
	</object>
	<object>
		<name>dish</name>
		<bndbox>
			<xmin>936</xmin>
			<ymin>212</ymin>
			<xmax>2320</xmax>
			<ymax>1164</ymax>
		</bndbox>
	</object>
	<object>
		<name>훈제연어</name>
		<bndbox>
			<xmin>1065</xmin>
			<ymin>404</ymin>
			<xmax>1841</xmax>
			<ymax>1077</ymax>
		</bndbox>
	</object>
</annotation>