<annotation>
	<folder>top생선조림사각배달꽁치조림q3</folder>
	<filename>top_생선조림_사각배달_꽁치조림_Q3_00022.JPG</filename>
	<path>/top생선조림사각배달꽁치조림q3/top_생선조림_사각배달_꽁치조림_Q3_00022.JPG</path>
	<source>
		<database>fooddata</database>
	</source>
	<size>
		<width>3008</width>
		<height>2000</height>
		<depth>3</depth>
	</size>
	<object>
		<name>ref_spoon</name>
		<bndbox>
			<xmin>773</xmin>
			<ymin>1652</ymin>
			<xmax>1117</xmax>
			<ymax>1882</ymax>
		</bndbox>
	</object>
	<object>
		<name>ref_fork</name>
		<bndbox>
			<xmin>838</xmin>
			<ymin>1410</ymin>
			<xmax>1186</xmax>
			<ymax>1564</ymax>
		</bndbox>
	</object>
	<object>
		<name>ref_coin</name>
		<bndbox>
			<xmin>1534</xmin>
			<ymin>1221</ymin>
			<xmax>1690</xmax>
			<ymax>1377</ymax>
		</bndbox>
	</object>
	<object>
		<name>dish</name>
		<bndbox>
			<xmin>676</xmin>
			<ymin>108</ymin>
			<xmax>1888</xmax>
			<ymax>1230</ymax>
		</bndbox>
	</object>
	<object>
		<name>꽁치조림</name>
		<bndbox>
			<xmin>867</xmin>
			<ymin>290</ymin>
			<xmax>1647</xmax>
			<ymax>1116</ymax>
		</bndbox>
	</object>
</annotation>