<annotation>
	<folder>side어육류면적사각배달훈제연어q3</folder>
	<filename>side_어육류면적_사각배달_훈제연어_Q3_00016.JPG</filename>
	<path>/side어육류면적사각배달훈제연어q3/side_어육류면적_사각배달_훈제연어_Q3_00016.JPG</path>
	<source>
		<database>fooddata</database>
	</source>
	<size>
		<width>3008</width>
		<height>2000</height>
		<depth>3</depth>
	</size>
	<object>
		<name>ref_spoon</name>
		<bndbox>
			<xmin>1890</xmin>
			<ymin>306</ymin>
			<xmax>2200</xmax>
			<ymax>682</ymax>
		</bndbox>
	</object>
	<object>
		<name>ref_fork</name>
		<bndbox>
			<xmin>2271</xmin>
			<ymin>322</ymin>
			<xmax>2500</xmax>
			<ymax>759</ymax>
		</bndbox>
	</object>
	<object>
		<name>ref_coin</name>
		<bndbox>
			<xmin>1143</xmin>
			<ymin>1587</ymin>
			<xmax>1433</xmax>
			<ymax>1785</ymax>
		</bndbox>
	</object>
	<object>
		<name>dish</name>
		<bndbox>
			<xmin>203</xmin>
			<ymin>195</ymin>
			<xmax>1966</xmax>
			<ymax>1495</ymax>
		</bndbox>
	</object>
	<object>
		<name>훈제연어</name>
		<bndbox>
			<xmin>584</xmin>
			<ymin>616</ymin>
			<xmax>1646</xmax>
			<ymax>1221</ymax>
		</bndbox>
	</object>
</annotation>