<annotation>
	<folder>side오므라이스사각배달오므라이스q1</folder>
	<filename>side_오므라이스_사각배달_오므라이스_Q1_00051.JPG</filename>
	<path>/side오므라이스사각배달오므라이스q1/side_오므라이스_사각배달_오므라이스_Q1_00051.JPG</path>
	<source>
		<database>fooddata</database>
	</source>
	<size>
		<width>3008</width>
		<height>2000</height>
		<depth>3</depth>
	</size>
	<object>
		<name>ref_spoon</name>
		<bndbox>
			<xmin>196</xmin>
			<ymin>548</ymin>
			<xmax>494</xmax>
			<ymax>912</ymax>
		</bndbox>
	</object>
	<object>
		<name>ref_fork</name>
		<bndbox>
			<xmin>614</xmin>
			<ymin>576</ymin>
			<xmax>814</xmax>
			<ymax>999</ymax>
		</bndbox>
	</object>
	<object>
		<name>ref_coin</name>
		<bndbox>
			<xmin>1907</xmin>
			<ymin>1650</ymin>
			<xmax>2144</xmax>
			<ymax>1826</ymax>
		</bndbox>
	</object>
	<object>
		<name>dish</name>
		<bndbox>
			<xmin>962</xmin>
			<ymin>284</ymin>
			<xmax>2635</xmax>
			<ymax>1422</ymax>
		</bndbox>
	</object>
	<object>
		<name>오므라이스</name>
		<bndbox>
			<xmin>1333</xmin>
			<ymin>533</ymin>
			<xmax>2121</xmax>
			<ymax>1053</ymax>
		</bndbox>
	</object>
</annotation>