<annotation>
	<folder>top생선조림접시코다리조림q3</folder>
	<filename>top_생선조림_접시_코다리조림_Q3_00017.JPG</filename>
	<path>/top생선조림접시코다리조림q3/top_생선조림_접시_코다리조림_Q3_00017.JPG</path>
	<source>
		<database>fooddata</database>
	</source>
	<size>
		<width>3008</width>
		<height>2000</height>
		<depth>3</depth>
	</size>
	<object>
		<name>ref_spoon</name>
		<bndbox>
			<xmin>990</xmin>
			<ymin>1576</ymin>
			<xmax>1476</xmax>
			<ymax>1859</ymax>
		</bndbox>
	</object>
	<object>
		<name>ref_fork</name>
		<bndbox>
			<xmin>1023</xmin>
			<ymin>1350</ymin>
			<xmax>1540</xmax>
			<ymax>1535</ymax>
		</bndbox>
	</object>
	<object>
		<name>ref_coin</name>
		<bndbox>
			<xmin>2144</xmin>
			<ymin>1028</ymin>
			<xmax>2324</xmax>
			<ymax>1208</ymax>
		</bndbox>
	</object>
	<object>
		<name>dish</name>
		<bndbox>
			<xmin>951</xmin>
			<ymin>64</ymin>
			<xmax>2118</xmax>
			<ymax>1198</ymax>
		</bndbox>
	</object>
	<object>
		<name>코다리조림</name>
		<bndbox>
			<xmin>1195</xmin>
			<ymin>378</ymin>
			<xmax>1784</xmax>
			<ymax>956</ymax>
		</bndbox>
	</object>
</annotation>