<annotation>
	<folder>top건더기국류뚝배기q1</folder>
	<filename>top_건더기국류_뚝배기_삼계탕_Q1_00028.JPG</filename>
	<path>/top건더기국류뚝배기삼계탕q1/top_건더기국류_뚝배기_삼계탕_Q1_00028.JPG</path>
	<source>
		<database>fooddata</database>
	</source>
	<size>
		<width>5472</width>
		<height>3648</height>
		<depth>3</depth>
	</size>
	<object>
		<name>ref_spoon</name>
		<bndbox>
			<xmin>1804</xmin>
			<ymin>2926</ymin>
			<xmax>2449</xmax>
			<ymax>3348</ymax>
		</bndbox>
	</object>
	<object>
		<name>ref_fork</name>
		<bndbox>
			<xmin>1795</xmin>
			<ymin>2451</ymin>
			<xmax>2467</xmax>
			<ymax>2747</ymax>
		</bndbox>
	</object>
	<object>
		<name>ref_coin</name>
		<bndbox>
			<xmin>1463</xmin>
			<ymin>1407</ymin>
			<xmax>1755</xmax>
			<ymax>1694</ymax>
		</bndbox>
	</object>
	<object>
		<name>dish</name>
		<bndbox>
			<xmin>2118</xmin>
			<ymin>229</ymin>
			<xmax>4327</xmax>
			<ymax>2407</ymax>
		</bndbox>
	</object>
	<object>
		<name>삼계탕</name>
		<bndbox>
			<xmin>2418</xmin>
			<ymin>609</ymin>
			<xmax>3933</xmax>
			<ymax>2111</ymax>
		</bndbox>
	</object>
</annotation>