<annotation>
	<folder>top밥류원형배달쌀밥q2</folder>
	<filename>top_밥류_원형배달_쌀밥_Q2_00025.JPG</filename>
	<path>/top밥류원형배달쌀밥q2/top_밥류_원형배달_쌀밥_Q2_00025.JPG</path>
	<source>
		<database>fooddata</database>
	</source>
	<size>
		<width>3008</width>
		<height>2000</height>
		<depth>3</depth>
	</size>
	<object>
		<name>ref_spoon</name>
		<bndbox>
			<xmin>505</xmin>
			<ymin>1326</ymin>
			<xmax>966</xmax>
			<ymax>1627</ymax>
		</bndbox>
	</object>
	<object>
		<name>ref_fork</name>
		<bndbox>
			<xmin>627</xmin>
			<ymin>1085</ymin>
			<xmax>1111</xmax>
			<ymax>1274</ymax>
		</bndbox>
	</object>
	<object>
		<name>ref_coin</name>
		<bndbox>
			<xmin>1796</xmin>
			<ymin>248</ymin>
			<xmax>2002</xmax>
			<ymax>467</ymax>
		</bndbox>
	</object>
	<object>
		<name>dish</name>
		<bndbox>
			<xmin>936</xmin>
			<ymin>193</ymin>
			<xmax>1853</xmax>
			<ymax>1120</ymax>
		</bndbox>
	</object>
	<object>
		<name>쌀밥</name>
		<bndbox>
			<xmin>1066</xmin>
			<ymin>377</ymin>
			<xmax>1743</xmax>
			<ymax>1020</ymax>
		</bndbox>
	</object>
</annotation>