<annotation>
	<folder>top파스타류원형배달토마토스파게티q3project-name</folder>
	<filename>top_파스타류_원형배달_토마토스파게티_Q3_00034.JPG</filename>
	<path>/top파스타류원형배달토마토스파게티q3/top_파스타류_원형배달_토마토스파게티_Q3_00034.JPG</path>
	<source>
		<database>fooddata</database>
	</source>
	<size>
		<width>3008</width>
		<height>2000</height>
		<depth>3</depth>
	</size>
	<object>
		<name>ref_spoon</name>
		<bndbox>
			<xmin>512</xmin>
			<ymin>181</ymin>
			<xmax>808</xmax>
			<ymax>672</ymax>
		</bndbox>
	</object>
	<object>
		<name>ref_fork</name>
		<bndbox>
			<xmin>876</xmin>
			<ymin>235</ymin>
			<xmax>1093</xmax>
			<ymax>733</ymax>
		</bndbox>
	</object>
	<object>
		<name>ref_coin</name>
		<bndbox>
			<xmin>1205</xmin>
			<ymin>1422</ymin>
			<xmax>1414</xmax>
			<ymax>1653</ymax>
		</bndbox>
	</object>
	<object>
		<name>dish</name>
		<bndbox>
			<xmin>1172</xmin>
			<ymin>174</ymin>
			<xmax>2640</xmax>
			<ymax>1624</ymax>
		</bndbox>
	</object>
	<object>
		<name>토마토스파게티</name>
		<bndbox>
			<xmin>1327</xmin>
			<ymin>408</ymin>
			<xmax>2384</xmax>
			<ymax>1480</ymax>
		</bndbox>
	</object>
</annotation>