<annotation>
	<folder>top오므라이스사각배달오므라이스q3</folder>
	<filename>top_오므라이스_사각배달_오므라이스_Q3_00009.JPG</filename>
	<path>/top오므라이스사각배달오므라이스q3/top_오므라이스_사각배달_오므라이스_Q3_00009.JPG</path>
	<source>
		<database>fooddata</database>
	</source>
	<size>
		<width>3008</width>
		<height>2000</height>
		<depth>3</depth>
	</size>
	<object>
		<name>ref_spoon</name>
		<bndbox>
			<xmin>2032</xmin>
			<ymin>271</ymin>
			<xmax>2297</xmax>
			<ymax>698</ymax>
		</bndbox>
	</object>
	<object>
		<name>ref_fork</name>
		<bndbox>
			<xmin>2358</xmin>
			<ymin>357</ymin>
			<xmax>2571</xmax>
			<ymax>809</ymax>
		</bndbox>
	</object>
	<object>
		<name>ref_coin</name>
		<bndbox>
			<xmin>655</xmin>
			<ymin>164</ymin>
			<xmax>854</xmax>
			<ymax>362</ymax>
		</bndbox>
	</object>
	<object>
		<name>dish</name>
		<bndbox>
			<xmin>488</xmin>
			<ymin>383</ymin>
			<xmax>1977</xmax>
			<ymax>1668</ymax>
		</bndbox>
	</object>
	<object>
		<name>오므라이스</name>
		<bndbox>
			<xmin>737</xmin>
			<ymin>667</ymin>
			<xmax>1534</xmax>
			<ymax>1556</ymax>
		</bndbox>
	</object>
</annotation>