<annotation>
	<folder>top부침개류사각배달녹두빈대떡q5</folder>
	<filename>top_부침개류_사각배달_녹두빈대떡_Q5_00055.JPG</filename>
	<path>/top부침개류사각배달녹두빈대떡q5/top_부침개류_사각배달_녹두빈대떡_Q5_00055.JPG</path>
	<source>
		<database>fooddata</database>
	</source>
	<size>
		<width>3008</width>
		<height>2000</height>
		<depth>3</depth>
	</size>
	<object>
		<name>ref_spoon</name>
		<bndbox>
			<xmin>750</xmin>
			<ymin>99</ymin>
			<xmax>998</xmax>
			<ymax>503</ymax>
		</bndbox>
	</object>
	<object>
		<name>ref_fork</name>
		<bndbox>
			<xmin>1091</xmin>
			<ymin>228</ymin>
			<xmax>1256</xmax>
			<ymax>658</ymax>
		</bndbox>
	</object>
	<object>
		<name>ref_coin</name>
		<bndbox>
			<xmin>1136</xmin>
			<ymin>1617</ymin>
			<xmax>1313</xmax>
			<ymax>1807</ymax>
		</bndbox>
	</object>
	<object>
		<name>dish</name>
		<bndbox>
			<xmin>1384</xmin>
			<ymin>77</ymin>
			<xmax>2387</xmax>
			<ymax>1421</ymax>
		</bndbox>
	</object>
	<object>
		<name>녹두빈대떡</name>
		<bndbox>
			<xmin>1522</xmin>
			<ymin>472</ymin>
			<xmax>2227</xmax>
			<ymax>1142</ymax>
		</bndbox>
	</object>
</annotation>