<annotation>
	<folder>side국물면류뚝배기일식우동q1</folder>
	<filename>side_국물면류_뚝배기_일식우동_Q1_00049.JPG</filename>
	<path>/side국물면류뚝배기일식우동q1/side_국물면류_뚝배기_일식우동_Q1_00049.JPG</path>
	<source>
		<database>fooddata</database>
	</source>
	<size>
		<width>3008</width>
		<height>2000</height>
		<depth>3</depth>
	</size>
	<object>
		<name>ref_spoon</name>
		<bndbox>
			<xmin>280</xmin>
			<ymin>703</ymin>
			<xmax>546</xmax>
			<ymax>1040</ymax>
		</bndbox>
	</object>
	<object>
		<name>ref_fork</name>
		<bndbox>
			<xmin>670</xmin>
			<ymin>747</ymin>
			<xmax>870</xmax>
			<ymax>1160</ymax>
		</bndbox>
	</object>
	<object>
		<name>ref_coin</name>
		<bndbox>
			<xmin>1007</xmin>
			<ymin>392</ymin>
			<xmax>1202</xmax>
			<ymax>525</ymax>
		</bndbox>
	</object>
	<object>
		<name>dish</name>
		<bndbox>
			<xmin>1069</xmin>
			<ymin>547</ymin>
			<xmax>2533</xmax>
			<ymax>1785</ymax>
		</bndbox>
	</object>
	<object>
		<name>일식우동</name>
		<bndbox>
			<xmin>1242</xmin>
			<ymin>902</ymin>
			<xmax>2369</xmax>
			<ymax>1532</ymax>
		</bndbox>
	</object>
</annotation>