<annotation>
	<folder>side비빔밥덮밥류냉면기회덮밥q4</folder>
	<filename>side_비빔밥덮밥류_냉면기_회덮밥_Q4_00003.JPG</filename>
	<path>/side비빔밥덮밥류냉면기회덮밥q4/side_비빔밥덮밥류_냉면기_회덮밥_Q4_00003.JPG</path>
	<source>
		<database>fooddata</database>
	</source>
	<size>
		<width>3008</width>
		<height>2000</height>
		<depth>3</depth>
	</size>
	<object>
		<name>ref_spoon</name>
		<bndbox>
			<xmin>2271</xmin>
			<ymin>612</ymin>
			<xmax>2531</xmax>
			<ymax>975</ymax>
		</bndbox>
	</object>
	<object>
		<name>ref_fork</name>
		<bndbox>
			<xmin>2674</xmin>
			<ymin>622</ymin>
			<xmax>2855</xmax>
			<ymax>1064</ymax>
		</bndbox>
	</object>
	<object>
		<name>ref_coin</name>
		<bndbox>
			<xmin>298</xmin>
			<ymin>1528</ymin>
			<xmax>514</xmax>
			<ymax>1690</ymax>
		</bndbox>
	</object>
	<object>
		<name>dish</name>
		<bndbox>
			<xmin>455</xmin>
			<ymin>206</ymin>
			<xmax>2018</xmax>
			<ymax>1349</ymax>
		</bndbox>
	</object>
	<object>
		<name>회덮밥</name>
		<bndbox>
			<xmin>715</xmin>
			<ymin>514</ymin>
			<xmax>1755</xmax>
			<ymax>1206</ymax>
		</bndbox>
	</object>
</annotation>