<annotation>
	<folder>top국류대접q2</folder>
	<filename>top_국류_대접_시래기된장국_Q2_00050.JPG</filename>
	<path>/top국류대접시래기된장국q2/top_국류_대접_시래기된장국_Q2_00050.JPG</path>
	<source>
		<database>fooddata</database>
	</source>
	<size>
		<width>5472</width>
		<height>3648</height>
		<depth>3</depth>
	</size>
	<object>
		<name>ref_spoon</name>
		<bndbox>
			<xmin>1450</xmin>
			<ymin>688</ymin>
			<xmax>1944</xmax>
			<ymax>1628</ymax>
		</bndbox>
	</object>
	<object>
		<name>ref_fork</name>
		<bndbox>
			<xmin>2239</xmin>
			<ymin>763</ymin>
			<xmax>2545</xmax>
			<ymax>1698</ymax>
		</bndbox>
	</object>
	<object>
		<name>ref_coin</name>
		<bndbox>
			<xmin>2932</xmin>
			<ymin>2917</ymin>
			<xmax>3297</xmax>
			<ymax>3303</ymax>
		</bndbox>
	</object>
	<object>
		<name>dish</name>
		<bndbox>
			<xmin>2733</xmin>
			<ymin>243</ymin>
			<xmax>5112</xmax>
			<ymax>2509</ymax>
		</bndbox>
	</object>
	<object>
		<name>시래기된장국</name>
		<bndbox>
			<xmin>2996</xmin>
			<ymin>656</ymin>
			<xmax>4683</xmax>
			<ymax>2321</ymax>
		</bndbox>
	</object>
</annotation>