<annotation>
	<folder>top볶음밥류접시삼선볶음밥q1</folder>
	<filename>top_볶음밥류_접시_삼선볶음밥_Q1_00034.JPG</filename>
	<path>/top볶음밥류접시삼선볶음밥q1/top_볶음밥류_접시_삼선볶음밥_Q1_00034.JPG</path>
	<source>
		<database>fooddata</database>
	</source>
	<size>
		<width>720</width>
		<height>480</height>
		<depth>3</depth>
	</size>
	<object>
		<name>ref_spoon</name>
		<bndbox>
			<xmin>253</xmin>
			<ymin>333</ymin>
			<xmax>343</xmax>
			<ymax>391</ymax>
		</bndbox>
	</object>
	<object>
		<name>ref_fork</name>
		<bndbox>
			<xmin>265</xmin>
			<ymin>409</ymin>
			<xmax>363</xmax>
			<ymax>449</ymax>
		</bndbox>
	</object>
	<object>
		<name>ref_coin</name>
		<bndbox>
			<xmin>426</xmin>
			<ymin>22</ymin>
			<xmax>463</xmax>
			<ymax>57</ymax>
		</bndbox>
	</object>
	<object>
		<name>dish</name>
		<bndbox>
			<xmin>227</xmin>
			<ymin>98</ymin>
			<xmax>613</xmax>
			<ymax>324</ymax>
		</bndbox>
	</object>
	<object>
		<name>삼선볶음밥</name>
		<bndbox>
			<xmin>276</xmin>
			<ymin>137</ymin>
			<xmax>527</xmax>
			<ymax>287</ymax>
		</bndbox>
	</object>
</annotation>