<annotation>
	<folder>top죽류대접호박죽q4</folder>
	<filename>top_죽류_대접_호박죽_Q4_00032.JPG</filename>
	<path>/top죽류대접호박죽q4/top_죽류_대접_호박죽_Q4_00032.JPG</path>
	<source>
		<database>fooddata</database>
	</source>
	<size>
		<width>5472</width>
		<height>3648</height>
		<depth>3</depth>
	</size>
	<object>
		<name>ref_spoon</name>
		<bndbox>
			<xmin>1117</xmin>
			<ymin>347</ymin>
			<xmax>1582</xmax>
			<ymax>1078</ymax>
		</bndbox>
	</object>
	<object>
		<name>ref_fork</name>
		<bndbox>
			<xmin>1798</xmin>
			<ymin>466</ymin>
			<xmax>2092</xmax>
			<ymax>1261</ymax>
		</bndbox>
	</object>
	<object>
		<name>ref_coin</name>
		<bndbox>
			<xmin>2688</xmin>
			<ymin>2890</ymin>
			<xmax>3000</xmax>
			<ymax>3225</ymax>
		</bndbox>
	</object>
	<object>
		<name>dish</name>
		<bndbox>
			<xmin>2172</xmin>
			<ymin>468</ymin>
			<xmax>4437</xmax>
			<ymax>2720</ymax>
		</bndbox>
	</object>
	<object>
		<name>호박죽</name>
		<bndbox>
			<xmin>2517</xmin>
			<ymin>808</ymin>
			<xmax>4101</xmax>
			<ymax>2396</ymax>
		</bndbox>
	</object>
</annotation>