<annotation>
	<folder>side어육류면적접시돼지갈비q2</folder>
	<filename>side_어육류면적_접시_돼지갈비_Q2_00055.JPG</filename>
	<path>/side어육류면적접시돼지갈비q2/side_어육류면적_접시_돼지갈비_Q2_00055.JPG</path>
	<source>
		<database>fooddata</database>
	</source>
	<size>
		<width>5472</width>
		<height>3648</height>
		<depth>3</depth>
	</size>
	<object>
		<name>ref_spoon</name>
		<bndbox>
			<xmin>1714</xmin>
			<ymin>2971</ymin>
			<xmax>2799</xmax>
			<ymax>3419</ymax>
		</bndbox>
	</object>
	<object>
		<name>ref_fork</name>
		<bndbox>
			<xmin>1849</xmin>
			<ymin>2478</ymin>
			<xmax>2879</xmax>
			<ymax>2832</ymax>
		</bndbox>
	</object>
	<object>
		<name>ref_coin</name>
		<bndbox>
			<xmin>4748</xmin>
			<ymin>632</ymin>
			<xmax>5080</xmax>
			<ymax>878</ymax>
		</bndbox>
	</object>
	<object>
		<name>dish</name>
		<bndbox>
			<xmin>1620</xmin>
			<ymin>699</ymin>
			<xmax>4874</xmax>
			<ymax>2196</ymax>
		</bndbox>
	</object>
	<object>
		<name>돼지갈비</name>
		<bndbox>
			<xmin>2593</xmin>
			<ymin>990</ymin>
			<xmax>4193</xmax>
			<ymax>2026</ymax>
		</bndbox>
	</object>
</annotation>