<annotation>
	<folder>side어육류면적접시돼지갈비q4</folder>
	<filename>side_어육류면적_접시_돼지갈비_Q4_00056.JPG</filename>
	<path>/side어육류면적접시돼지갈비q4/side_어육류면적_접시_돼지갈비_Q4_00056.JPG</path>
	<source>
		<database>fooddata</database>
	</source>
	<size>
		<width>5472</width>
		<height>3648</height>
		<depth>3</depth>
	</size>
	<object>
		<name>ref_spoon</name>
		<bndbox>
			<xmin>1620</xmin>
			<ymin>2922</ymin>
			<xmax>2705</xmax>
			<ymax>3393</ymax>
		</bndbox>
	</object>
	<object>
		<name>ref_fork</name>
		<bndbox>
			<xmin>1777</xmin>
			<ymin>2563</ymin>
			<xmax>2812</xmax>
			<ymax>2922</ymax>
		</bndbox>
	</object>
	<object>
		<name>ref_coin</name>
		<bndbox>
			<xmin>2252</xmin>
			<ymin>506</ymin>
			<xmax>2566</xmax>
			<ymax>739</ymax>
		</bndbox>
	</object>
	<object>
		<name>dish</name>
		<bndbox>
			<xmin>1333</xmin>
			<ymin>753</ymin>
			<xmax>4618</xmax>
			<ymax>2263</ymax>
		</bndbox>
	</object>
	<object>
		<name>돼지갈비</name>
		<bndbox>
			<xmin>1808</xmin>
			<ymin>1040</ymin>
			<xmax>4394</xmax>
			<ymax>2165</ymax>
		</bndbox>
	</object>
</annotation>