<annotation>
	<folder>side국물면류원형배달콩국수q4</folder>
	<filename>side_국물면류_원형배달_콩국수_Q4_00018.JPG</filename>
	<path>/side국물면류원형배달콩국수q4/side_국물면류_원형배달_콩국수_Q4_00018.JPG</path>
	<source>
		<database>fooddata</database>
	</source>
	<size>
		<width>3008</width>
		<height>2000</height>
		<depth>3</depth>
	</size>
	<object>
		<name>ref_spoon</name>
		<bndbox>
			<xmin>772</xmin>
			<ymin>1550</ymin>
			<xmax>1247</xmax>
			<ymax>1807</ymax>
		</bndbox>
	</object>
	<object>
		<name>ref_fork</name>
		<bndbox>
			<xmin>856</xmin>
			<ymin>1280</ymin>
			<xmax>1371</xmax>
			<ymax>1528</ymax>
		</bndbox>
	</object>
	<object>
		<name>ref_coin</name>
		<bndbox>
			<xmin>2169</xmin>
			<ymin>951</ymin>
			<xmax>2378</xmax>
			<ymax>1111</ymax>
		</bndbox>
	</object>
	<object>
		<name>dish</name>
		<bndbox>
			<xmin>821</xmin>
			<ymin>87</ymin>
			<xmax>2122</xmax>
			<ymax>1233</ymax>
		</bndbox>
	</object>
	<object>
		<name>콩국수</name>
		<bndbox>
			<xmin>895</xmin>
			<ymin>286</ymin>
			<xmax>2048</xmax>
			<ymax>896</ymax>
		</bndbox>
	</object>
</annotation>