<annotation>
	<folder>top밥류밥그릇콩밥q4</folder>
	<filename>top_밥류_밥그릇_콩밥_Q4_00037.JPG</filename>
	<path>/top밥류밥그릇콩밥q4/top_밥류_밥그릇_콩밥_Q4_00037.JPG</path>
	<source>
		<database>fooddata</database>
	</source>
	<size>
		<width>5472</width>
		<height>3648</height>
		<depth>3</depth>
	</size>
	<object>
		<name>ref_spoon</name>
		<bndbox>
			<xmin>1248</xmin>
			<ymin>273</ymin>
			<xmax>1808</xmax>
			<ymax>1179</ymax>
		</bndbox>
	</object>
	<object>
		<name>ref_fork</name>
		<bndbox>
			<xmin>2014</xmin>
			<ymin>296</ymin>
			<xmax>2386</xmax>
			<ymax>1313</ymax>
		</bndbox>
	</object>
	<object>
		<name>ref_coin</name>
		<bndbox>
			<xmin>2960</xmin>
			<ymin>2949</ymin>
			<xmax>3381</xmax>
			<ymax>3375</ymax>
		</bndbox>
	</object>
	<object>
		<name>dish</name>
		<bndbox>
			<xmin>2431</xmin>
			<ymin>892</ymin>
			<xmax>4421</xmax>
			<ymax>2832</ymax>
		</bndbox>
	</object>
	<object>
		<name>콩밥</name>
		<bndbox>
			<xmin>2566</xmin>
			<ymin>1049</ymin>
			<xmax>4278</xmax>
			<ymax>2689</ymax>
		</bndbox>
	</object>
</annotation>