<annotation>
	<folder>side반찬부피접시어묵볶음q4</folder>
	<filename>side_반찬부피_접시_어묵볶음_Q4_00020.JPG</filename>
	<path>/side반찬부피접시어묵볶음q4/side_반찬부피_접시_어묵볶음_Q4_00020.JPG</path>
	<source>
		<database>fooddata</database>
	</source>
	<size>
		<width>3008</width>
		<height>2000</height>
		<depth>3</depth>
	</size>
	<object>
		<name>ref_spoon</name>
		<bndbox>
			<xmin>683</xmin>
			<ymin>1516</ymin>
			<xmax>1128</xmax>
			<ymax>1803</ymax>
		</bndbox>
	</object>
	<object>
		<name>ref_fork</name>
		<bndbox>
			<xmin>809</xmin>
			<ymin>1287</ymin>
			<xmax>1312</xmax>
			<ymax>1553</ymax>
		</bndbox>
	</object>
	<object>
		<name>ref_coin</name>
		<bndbox>
			<xmin>2403</xmin>
			<ymin>693</ymin>
			<xmax>2610</xmax>
			<ymax>845</ymax>
		</bndbox>
	</object>
	<object>
		<name>dish</name>
		<bndbox>
			<xmin>850</xmin>
			<ymin>290</ymin>
			<xmax>2256</xmax>
			<ymax>1187</ymax>
		</bndbox>
	</object>
	<object>
		<name>어묵볶음</name>
		<bndbox>
			<xmin>1032</xmin>
			<ymin>415</ymin>
			<xmax>2062</xmax>
			<ymax>1081</ymax>
		</bndbox>
	</object>
</annotation>