<annotation>
	<folder>side파스타류낮고큰파스타볼크림소스스파게티q5</folder>
	<filename>side_파스타류_낮고큰파스타볼_크림소스스파게티_Q5_00053.JPG</filename>
	<path>/side파스타류낮고큰파스타볼크림소스스파게티q5/side_파스타류_낮고큰파스타볼_크림소스스파게티_Q5_00053.JPG</path>
	<source>
		<database>fooddata</database>
	</source>
	<size>
		<width>5472</width>
		<height>3648</height>
		<depth>3</depth>
	</size>
	<object>
		<name>ref_spoon</name>
		<bndbox>
			<xmin>548</xmin>
			<ymin>1046</ymin>
			<xmax>1045</xmax>
			<ymax>1685</ymax>
		</bndbox>
	</object>
	<object>
		<name>ref_fork</name>
		<bndbox>
			<xmin>1123</xmin>
			<ymin>1098</ymin>
			<xmax>1465</xmax>
			<ymax>1872</ymax>
		</bndbox>
	</object>
	<object>
		<name>ref_coin</name>
		<bndbox>
			<xmin>3317</xmin>
			<ymin>2989</ymin>
			<xmax>3717</xmax>
			<ymax>3318</ymax>
		</bndbox>
	</object>
	<object>
		<name>dish</name>
		<bndbox>
			<xmin>1626</xmin>
			<ymin>395</ymin>
			<xmax>4485</xmax>
			<ymax>2453</ymax>
		</bndbox>
	</object>
	<object>
		<name>크림소스스파게티</name>
		<bndbox>
			<xmin>2129</xmin>
			<ymin>924</ymin>
			<xmax>3988</xmax>
			<ymax>2298</ymax>
		</bndbox>
	</object>
</annotation>