<annotation>
	<folder>top국류대접소고기무국q5</folder>
	<filename>top_국류_대접_소고기무국_Q5_00026.JPG</filename>
	<path>/top국류대접소고기무국q5/top_국류_대접_소고기무국_Q5_00026.JPG</path>
	<source>
		<database>fooddata</database>
	</source>
	<size>
		<width>5472</width>
		<height>3648</height>
		<depth>3</depth>
	</size>
	<object>
		<name>ref_spoon</name>
		<bndbox>
			<xmin>1724</xmin>
			<ymin>2989</ymin>
			<xmax>2482</xmax>
			<ymax>3462</ymax>
		</bndbox>
	</object>
	<object>
		<name>ref_fork</name>
		<bndbox>
			<xmin>1755</xmin>
			<ymin>2492</ymin>
			<xmax>2575</xmax>
			<ymax>2795</ymax>
		</bndbox>
	</object>
	<object>
		<name>ref_coin</name>
		<bndbox>
			<xmin>1549</xmin>
			<ymin>866</ymin>
			<xmax>1878</xmax>
			<ymax>1175</ymax>
		</bndbox>
	</object>
	<object>
		<name>dish</name>
		<bndbox>
			<xmin>2058</xmin>
			<ymin>414</ymin>
			<xmax>4085</xmax>
			<ymax>2427</ymax>
		</bndbox>
	</object>
	<object>
		<name>소고기무국</name>
		<bndbox>
			<xmin>2207</xmin>
			<ymin>633</ymin>
			<xmax>3910</xmax>
			<ymax>2305</ymax>
		</bndbox>
	</object>
</annotation>