<annotation>
	<folder>side건더기류원형배달알탕q4</folder>
	<filename>side_건더기국류_원형배달_알탕_Q4_00035.JPG</filename>
	<path>/side건더기국류원형배달알탕q4/side_건더기국류_원형배달_알탕_Q4_00035.JPG</path>
	<source>
		<database>fooddata</database>
	</source>
	<size>
		<width>3008</width>
		<height>2000</height>
		<depth>3</depth>
	</size>
	<object>
		<name>ref_spoon</name>
		<bndbox>
			<xmin>637</xmin>
			<ymin>1468</ymin>
			<xmax>1039</xmax>
			<ymax>1693</ymax>
		</bndbox>
	</object>
	<object>
		<name>ref_fork</name>
		<bndbox>
			<xmin>721</xmin>
			<ymin>1210</ymin>
			<xmax>1169</xmax>
			<ymax>1427</ymax>
		</bndbox>
	</object>
	<object>
		<name>ref_coin</name>
		<bndbox>
			<xmin>2082</xmin>
			<ymin>187</ymin>
			<xmax>2251</xmax>
			<ymax>294</ymax>
		</bndbox>
	</object>
	<object>
		<name>dish</name>
		<bndbox>
			<xmin>964</xmin>
			<ymin>148</ymin>
			<xmax>2054</xmax>
			<ymax>1161</ymax>
		</bndbox>
	</object>
	<object>
		<name>알탕</name>
		<bndbox>
			<xmin>1028</xmin>
			<ymin>315</ymin>
			<xmax>1990</xmax>
			<ymax>775</ymax>
		</bndbox>
	</object>
</annotation>