<annotation>
	<folder>top건더기국류뚝배기갈비탕</folder>
	<filename>top_건더기국류_뚝배기_갈비탕_Q4_00047.JPG</filename>
	<path>/top건더기국류뚝배기갈비탕q4/top_건더기국류_뚝배기_갈비탕_Q4_00047.JPG</path>
	<source>
		<database>fooddata</database>
	</source>
	<size>
		<width>3008</width>
		<height>2000</height>
		<depth>3</depth>
	</size>
	<object>
		<name>ref_spoon</name>
		<bndbox>
			<xmin>222</xmin>
			<ymin>219</ymin>
			<xmax>517</xmax>
			<ymax>658</ymax>
		</bndbox>
	</object>
	<object>
		<name>ref_fork</name>
		<bndbox>
			<xmin>624</xmin>
			<ymin>201</ymin>
			<xmax>823</xmax>
			<ymax>708</ymax>
		</bndbox>
	</object>
	<object>
		<name>ref_coin</name>
		<bndbox>
			<xmin>1282</xmin>
			<ymin>1728</ymin>
			<xmax>1488</xmax>
			<ymax>1945</ymax>
		</bndbox>
	</object>
	<object>
		<name>dish</name>
		<bndbox>
			<xmin>1094</xmin>
			<ymin>175</ymin>
			<xmax>2478</xmax>
			<ymax>1530</ymax>
		</bndbox>
	</object>
	<object>
		<name>갈비탕</name>
		<bndbox>
			<xmin>1170</xmin>
			<ymin>329</ymin>
			<xmax>2332</xmax>
			<ymax>1465</ymax>
		</bndbox>
	</object>
</annotation>