<annotation>
	<folder>top국류뚝배기전주콩나물국밥q3</folder>
	<filename>top_국류_뚝배기_전주콩나물국밥_Q3_00050.JPG</filename>
	<path>/top국류뚝배기전주콩나물국밥q3/top_국류_뚝배기_전주콩나물국밥_Q3_00050.JPG</path>
	<source>
		<database>fooddata</database>
	</source>
	<size>
		<width>5472</width>
		<height>3648</height>
		<depth>3</depth>
	</size>
	<object>
		<name>ref_spoon</name>
		<bndbox>
			<xmin>678</xmin>
			<ymin>546</ymin>
			<xmax>1193</xmax>
			<ymax>1372</ymax>
		</bndbox>
	</object>
	<object>
		<name>ref_fork</name>
		<bndbox>
			<xmin>1341</xmin>
			<ymin>686</ymin>
			<xmax>1691</xmax>
			<ymax>1567</ymax>
		</bndbox>
	</object>
	<object>
		<name>ref_coin</name>
		<bndbox>
			<xmin>3991</xmin>
			<ymin>2830</ymin>
			<xmax>4381</xmax>
			<ymax>3227</ymax>
		</bndbox>
	</object>
	<object>
		<name>dish</name>
		<bndbox>
			<xmin>1769</xmin>
			<ymin>125</ymin>
			<xmax>4638</xmax>
			<ymax>2962</ymax>
		</bndbox>
	</object>
	<object>
		<name>전주콩나물국밥</name>
		<bndbox>
			<xmin>2042</xmin>
			<ymin>460</ymin>
			<xmax>4334</xmax>
			<ymax>2705</ymax>
		</bndbox>
	</object>
</annotation>