<annotation>
	<folder>side국류냄비매운탕q4</folder>
	<filename>side_국류_냄비_매운탕_Q4_00041.JPG</filename>
	<path>/side국류냄비매운탕q4/side_국류_냄비_매운탕_Q4_00041.JPG</path>
	<source>
		<database>fooddata</database>
	</source>
	<size>
		<width>3008</width>
		<height>2000</height>
		<depth>3</depth>
	</size>
	<object>
		<name>ref_spoon</name>
		<bndbox>
			<xmin>447</xmin>
			<ymin>1509</ymin>
			<xmax>890</xmax>
			<ymax>1779</ymax>
		</bndbox>
	</object>
	<object>
		<name>ref_fork</name>
		<bndbox>
			<xmin>514</xmin>
			<ymin>1296</ymin>
			<xmax>997</xmax>
			<ymax>1534</ymax>
		</bndbox>
	</object>
	<object>
		<name>ref_coin</name>
		<bndbox>
			<xmin>2096</xmin>
			<ymin>1608</ymin>
			<xmax>2320</xmax>
			<ymax>1800</ymax>
		</bndbox>
	</object>
	<object>
		<name>dish</name>
		<bndbox>
			<xmin>667</xmin>
			<ymin>207</ymin>
			<xmax>1979</xmax>
			<ymax>1176</ymax>
		</bndbox>
	</object>
	<object>
		<name>매운탕</name>
		<bndbox>
			<xmin>766</xmin>
			<ymin>413</ymin>
			<xmax>1855</xmax>
			<ymax>1041</ymax>
		</bndbox>
	</object>
</annotation>