<annotation>
	<folder>top비빔면류냉면기회냉면q3</folder>
	<filename>top_비빔면류_냉면기_회냉면_Q3_00048.JPG</filename>
	<path>/top비빔면류냉면기회냉면q3/top_비빔면류_냉면기_회냉면_Q3_00048.JPG</path>
	<source>
		<database>fooddata</database>
	</source>
	<size>
		<width>3008</width>
		<height>2000</height>
		<depth>3</depth>
	</size>
	<object>
		<name>ref_spoon</name>
		<bndbox>
			<xmin>218</xmin>
			<ymin>367</ymin>
			<xmax>539</xmax>
			<ymax>794</ymax>
		</bndbox>
	</object>
	<object>
		<name>ref_fork</name>
		<bndbox>
			<xmin>615</xmin>
			<ymin>388</ymin>
			<xmax>823</xmax>
			<ymax>840</ymax>
		</bndbox>
	</object>
	<object>
		<name>ref_coin</name>
		<bndbox>
			<xmin>1067</xmin>
			<ymin>134</ymin>
			<xmax>1265</xmax>
			<ymax>327</ymax>
		</bndbox>
	</object>
	<object>
		<name>dish</name>
		<bndbox>
			<xmin>970</xmin>
			<ymin>286</ymin>
			<xmax>2505</xmax>
			<ymax>1810</ymax>
		</bndbox>
	</object>
	<object>
		<name>회냉면</name>
		<bndbox>
			<xmin>1148</xmin>
			<ymin>632</ymin>
			<xmax>2236</xmax>
			<ymax>1699</ymax>
		</bndbox>
	</object>
</annotation>