<annotation>
	<folder>side반찬면적접시깻잎장아찌q2</folder>
	<filename>side_반찬면적_접시_깻잎장아찌_Q2_00006.JPG</filename>
	<path>/side반찬면적접시깻잎장아찌q2/side_반찬면적_접시_깻잎장아찌_Q2_00006.JPG</path>
	<source>
		<database>fooddata</database>
	</source>
	<size>
		<width>3008</width>
		<height>2000</height>
		<depth>3</depth>
	</size>
	<object>
		<name>ref_spoon</name>
		<bndbox>
			<xmin>1880</xmin>
			<ymin>528</ymin>
			<xmax>2167</xmax>
			<ymax>876</ymax>
		</bndbox>
	</object>
	<object>
		<name>ref_fork</name>
		<bndbox>
			<xmin>2295</xmin>
			<ymin>525</ymin>
			<xmax>2511</xmax>
			<ymax>926</ymax>
		</bndbox>
	</object>
	<object>
		<name>ref_coin</name>
		<bndbox>
			<xmin>135</xmin>
			<ymin>1273</ymin>
			<xmax>369</xmax>
			<ymax>1436</ymax>
		</bndbox>
	</object>
	<object>
		<name>dish</name>
		<bndbox>
			<xmin>624</xmin>
			<ymin>656</ymin>
			<xmax>1806</xmax>
			<ymax>1479</ymax>
		</bndbox>
	</object>
	<object>
		<name>깻잎장아찌</name>
		<bndbox>
			<xmin>926</xmin>
			<ymin>727</ymin>
			<xmax>1571</xmax>
			<ymax>1330</ymax>
		</bndbox>
	</object>
</annotation>