<annotation>
	<folder>side죽류대접호박죽q5</folder>
	<filename>side_죽류_대접_호박죽_Q5_00017.JPG</filename>
	<path>/side죽류대접호박죽q5/side_죽류_대접_호박죽_Q5_00017.JPG</path>
	<source>
		<database>fooddata</database>
	</source>
	<size>
		<width>5472</width>
		<height>3648</height>
		<depth>3</depth>
	</size>
	<object>
		<name>ref_spoon</name>
		<bndbox>
			<xmin>3270</xmin>
			<ymin>806</ymin>
			<xmax>3775</xmax>
			<ymax>1569</ymax>
		</bndbox>
	</object>
	<object>
		<name>ref_fork</name>
		<bndbox>
			<xmin>3974</xmin>
			<ymin>828</ymin>
			<xmax>4328</xmax>
			<ymax>1660</ymax>
		</bndbox>
	</object>
	<object>
		<name>ref_coin</name>
		<bndbox>
			<xmin>4801</xmin>
			<ymin>2299</ymin>
			<xmax>5230</xmax>
			<ymax>2600</ymax>
		</bndbox>
	</object>
	<object>
		<name>dish</name>
		<bndbox>
			<xmin>709</xmin>
			<ymin>565</ymin>
			<xmax>3190</xmax>
			<ymax>2299</ymax>
		</bndbox>
	</object>
	<object>
		<name>호박죽</name>
		<bndbox>
			<xmin>1010</xmin>
			<ymin>887</ymin>
			<xmax>2964</xmax>
			<ymax>2224</ymax>
		</bndbox>
	</object>
</annotation>