<annotation>
	<folder>side국류냉면기물회q1</folder>
	<filename>side_국류_냉면기_물회_Q1_00028.JPG</filename>
	<path>/side국류냉면기물회q1/side_국류_냉면기_물회_Q1_00028.JPG</path>
	<source>
		<database>fooddata</database>
	</source>
	<size>
		<width>3008</width>
		<height>2000</height>
		<depth>3</depth>
	</size>
	<object>
		<name>ref_spoon</name>
		<bndbox>
			<xmin>783</xmin>
			<ymin>1550</ymin>
			<xmax>1235</xmax>
			<ymax>1775</ymax>
		</bndbox>
	</object>
	<object>
		<name>ref_fork</name>
		<bndbox>
			<xmin>826</xmin>
			<ymin>1332</ymin>
			<xmax>1310</xmax>
			<ymax>1542</ymax>
		</bndbox>
	</object>
	<object>
		<name>ref_coin</name>
		<bndbox>
			<xmin>166</xmin>
			<ymin>1396</ymin>
			<xmax>379</xmax>
			<ymax>1542</ymax>
		</bndbox>
	</object>
	<object>
		<name>dish</name>
		<bndbox>
			<xmin>1013</xmin>
			<ymin>128</ymin>
			<xmax>2420</xmax>
			<ymax>1138</ymax>
		</bndbox>
	</object>
	<object>
		<name>물회</name>
		<bndbox>
			<xmin>1228</xmin>
			<ymin>542</ymin>
			<xmax>2202</xmax>
			<ymax>921</ymax>
		</bndbox>
	</object>
</annotation>